nacl_encrypted_fields/__init__.py
nacl_encrypted_fields/fields.py
nacl_encrypted_fields/backends/__init__.py
nacl_encrypted_fields/backends/cryptowrapper.py
nacl_encrypted_fields/backends/naclwrapper.py
nacl_encrypted_fields/management/__init__.py
nacl_encrypted_fields/management/commands/__init__.py
nacl_encrypted_fields/management/commands/convertkey.py
nacl_encrypted_fields/management/commands/createkey.py
tests/backends/__init__.py
tests/backends/testcryptowrapper.py
tests/models/__init__.py
tests/models/testmodel.py
django_nacl_fields-4.1.0.dist-info/LICENSE
django_nacl_fields-4.1.0.dist-info/METADATA
django_nacl_fields-4.1.0.dist-info/WHEEL
django_nacl_fields-4.1.0.dist-info/top_level.txt
django_nacl_fields-4.1.0.dist-info/RECORD
